{
    "0900": {
        "lat": 25.1330603,
        "lng": 121.739254
    },
    "0930": {
        "lat": 25.0930593,
        "lng": 121.7139326
    },
    "0980": {
        "lat": 25.0530895,
        "lng": 121.6069541
    },
    "0990": {
        "lat": 25.049831,
        "lng": 121.5775002
    },
    "1000": {
        "lat": 25.0474428,
        "lng": 121.5170955
    },
    "1020": {
        "lat": 25.0141868,
        "lng": 121.4635386
    },
    "1040": {
        "lat": 24.9913972,
        "lng": 121.4244296
    },
    "1080": {
        "lat": 24.98892,
        "lng": 121.31444
    },
    "1100": {
        "lat": 24.9536291,
        "lng": 121.2255932
    },
    "1210": {
        "lat": 24.8015877,
        "lng": 120.9715883
    },
    "1250": {
        "lat": 24.686589,
        "lng": 120.8805627
    },
    "3160": {
        "lat": 24.57002,
        "lng": 120.822343
    },
    "3230": {
        "lat": 24.2541919,
        "lng": 120.7234816
    },
    "3300": {
        "lat": 24.1364405,
        "lng": 120.6837261
    },
    "3360": {
        "lat": 24.0816236,
        "lng": 120.5383779
    },
    "3390": {
        "lat": 23.9593084,
        "lng": 120.569582
    },
    "3470": {
        "lat": 23.711922,
        "lng": 120.5410043
    },
    "4080": {
        "lat": 23.4791464,
        "lng": 120.4411545
    },
    "4120": {
        "lat": 23.3067276,
        "lng": 120.3230735
    },
    "4220": {
        "lat": 22.9970861,
        "lng": 120.2129832
    },
    "4340": {
        "lat": 22.6875442,
        "lng": 120.3067878
    },
    "4400": {
        "lat": 22.6394924,
        "lng": 120.302583
    },
    "5000": {
        "lat": 22.6689173,
        "lng": 120.4860729
    },
    "5050": {
        "lat": 22.550206,
        "lng": 120.535892
    },
    "7190": {
        "lat": 24.7552923,
        "lng": 121.7583174
    },
    "7130": {
        "lat": 24.6089299,
        "lng": 121.8276828
    },
    "7000": {
        "lat": 23.9933133,
        "lng": 121.6012455
    },
    "6110": {
        "lat": 23.33152,
        "lng": 121.31172
    },
    "6000": {
        "lat": 22.7937365,
        "lng": 121.1230986
    }
}